Workbook

Sheet Inventory
A1: Products | B1: Price/stock | C1: Total stock | D1: Customer Code | E1: Customer Name | F1: Opening Stock | G1: 46003 | H1: 13/12/2025 | I1: 14/01/2026 | J1: 16/0102026
A2: Gala | B2: 10500 | C2: =SUM(F2:BZ2) -> 130 | D2: 001 | E2: Mama Ada | F2: 100 | G2: 20 | I2: 10
A3: Mini Chin Chin Packs | B3: 20000 | C3: =SUM(F3:BZ3) -> 78 | D3: 002 | E3: Funmi Airport | F3: 50 | H3: 13 | J3: 15
A4: Peanut Snacks | B4: 12300 | C4: =SUM(F4:BZ4) -> 114 | D4: 003 | E4: JC Global | F4: 45 | G4: 60 | I4: 9
A5: Cheese Balls | B5: 14680 | C5: =SUM(F5:BZ5) -> 160 | D5: 004 | E5: KC | F5: 150 | J5: 10
A6: Short_Bread | B6: 16530 | C6: =SUM(F6:BZ6) -> 95 | D6: 005 | E6: Chidi Market | F6: 83 | I6: 12
A7: Nice_Biscuits | B7: 8200 | C7: =SUM(F7:BZ7) -> 117 | D7: 006 | E7: Angela N | F7: 57 | H7: 40 | J7: 20
A8: Beloxxi Cream Crackers | B8: 16110 | C8: =SUM(F8:BZ8) -> 74 | D8: 007 | E8: Theo Wire road | F8: 30 | G8: 28 | I8: 16
A9: Digestives | B9: 6800 | C9: =SUM(F9:BZ9) -> 214 | D9: 008 | E9: Pat Y | F9: 200 | J9: 14
A10: Ginger_Biscuits | B10: 5210 | C10: =SUM(F10:BZ10) -> 25 | D10: 009 | E10: Iyaro Bar | F10: 25
A11: Chocolate Biscuits | B11: 11950 | C11: =SUM(F11:BZ11) -> 128 | D11: 10 | E11: Lucky Cookroad | F11: 80 | H11: 18 | J11: 30
A12: Cabin Biscuit | B12: 4200 | C12: =SUM(F12:BZ12) -> 70 | D12: 11 | E12: Mama Emma | F12: 60 | G12: 10
A13: McVities Digestive: | B13: 5900 | C13: =SUM(F13:BZ13) -> 106 | D13: 12 | E13: Jesse | F13: 94 | J13: 12
A14: Gala Biscuit: | B14: 7270 | C14: =SUM(F14:BZ14) -> 75 | D14: 13 | E14: Goodness 70 | F14: 61 | I14: 14
A15: Royal Cream Crackers: | B15: 15100 | C15: =SUM(F15:BZ15) -> 78 | D15: 14 | E15: Aje Move | F15: 8 | G15: 20 | J15: 50
A16: Choco-Chip Biscuit: | B16: 10800 | C16: =SUM(F16:BZ16) -> 36 | D16: 15 | E16: Lizzy Enterprize | F16: 10 | J16: 26
A17: Golden Morn Biscuit: | B17: 13090 | C17: =SUM(F17:BZ17) -> 29 | D17: 16 | E17: Supperman 001 | F17: 18 | H17: 11
A18: Rich Tea Biscuit: | B18: 6200 | C18: =SUM(F18:BZ18) -> 96 | D18: 17 | E18: Emenike Yellow | F18: 28 | I18: 30 | J18: 38
A19: Golden Morn Biscuit: | B19: 5600 | C19: =SUM(F19:BZ19) -> 50 | D19: 18 | E19: Moses Hiltop | F19: 33 | G19: 17
A20: Rich Tea Biscuit: | B20: 4580 | C20: =SUM(F20:BZ20) -> 50 | F20: 40 | I20: 10
C21: =SUM(F21:BZ21) -> 0
C22: =SUM(F22:BZ22) -> 0
C23: =SUM(F23:BZ23) -> 0
C24: =SUM(F24:BZ24) -> 0
C25: =SUM(F25:BZ25) -> 0
C26: =SUM(F26:BZ26) -> 0
C27: =SUM(F27:BZ27) -> 0
C28: =SUM(F28:BZ28) -> 0
C29: =SUM(F29:BZ29) -> 0
C30: =SUM(F30:BZ30) -> 0
C31: =SUM(F31:BZ31) -> 0
C32: =SUM(F32:BZ32) -> 0
... C3004: =SUM(F3004:BZ3004) -> 0

Sheet Sales_Person
A1: Posting Date | B1: Customer Code | C1: Customer Name | D1: Particulars | E1: Reference | F1: Products | G1: Quantity | H1: Qty Purchase | I1: Price/Product | J1: Total Price | K1: Payment Received | L1: Debit | M1: Remark/Teller_Date/Number | N1: Stock Balance
A2: 46032 | B2: 001 | C2: {=IF(B2="", "", XLOOKUP(B2, Inventory!D:D,Inventory!E:E,"No Name Found"))} -> Mama Ada | D2: Credit | E2: Transfer | F2: Gala | G2: =IF(F2="", "", VLOOKUP(F2, Inventory!A:BZ, 3, FALSE) - SUMIF($F$1:$F1, F2, $H$1:$H1)) -> 130 | H2: 20 | I2: 10500 | J2: {=IF(H2:H5998="", "", H2:H5998 * I2:I5998)} -> 210000 | K2: 150000 | L2: {=IF(J2:J5998="", "", K2:K5998 - J2:J5998)} -> -60000 | N2: {=IF(G2:G5998="", "", G2:G5998 - H2:H5998)} -> 110
A3: 46034 | B3: 002 | C3: {=IF(B3="", "", XLOOKUP(B3, Inventory!D:D,Inventory!E:E,"No Name Found"))} -> Funmi Airport | D3: Credit | E3: Transfer | F3: Mini Chin Chin Packs | G3: =IF(F3="", "", VLOOKUP(F3, Inventory!A:BZ, 3, FALSE) - SUMIF($F$1:$F2, F3, $H$1:$H2)) -> 78 | H3: 40 | I3: 20000 | J3: 800000 | K3: 800000 | L3: 0 | N3: 38
A4: 46037 | B4: 001 | C4: {=IF(B4="", "", XLOOKUP(B4, Inventory!D:D,Inventory!E:E,"No Name Found"))} -> Mama Ada | D4: Credit | E4: Transfer | F4: Peanut Snacks | G4: =IF(F4="", "", VLOOKUP(F4, Inventory!A:BZ, 3, FALSE) - SUMIF($F$1:$F3, F4, $H$1:$H3)) -> 114 | H4: 50 | I4: 12300 | J4: 615000 | K4: 1000000 | L4: 385000 | N4: 64
A5: 46042 | B5: 004 | C5: {=IF(B5="", "", XLOOKUP(B5, Inventory!D:D,Inventory!E:E,"No Name Found"))} -> KC | D5: Debit | F5: Cheese Balls | G5: =IF(F5="", "", VLOOKUP(F5, Inventory!A:BZ, 3, FALSE) - SUMIF($F$1:$F4, F5, $H$1:$H4)) -> 160 | H5: 20 | I5: 14680 | J5: 293600 | L5: -293600 | N5: 140
A6: 46044 | B6: 005 | C6: {=IF(B6="", "", XLOOKUP(B6, Inventory!D:D,Inventory!E:E,"No Name Found"))} -> Chidi Market | D6: Credit | E6: Cash | F6: Short_Bread | G6: =IF(F6="", "", VLOOKUP(F6, Inventory!A:BZ, 3, FALSE) - SUMIF($F$1:$F5, F6, $H$1:$H5)) -> 95 | H6: 35 | I6: 16530 | J6: 578550 | K6: 500000 | L6: -78550 | N6: 60
A7: 46044 | B7: 006 | C7: {=IF(B7="", "", XLOOKUP(B7, Inventory!D:D,Inventory!E:E,"No Name Found"))} -> Angela N | D7: Debit | F7: Gala | G7: =IF(F7="", "", VLOOKUP(F7, Inventory!A:BZ, 3, FALSE) - SUMIF($F$1:$F6, F7, $H$1:$H6)) -> 110 | H7: 10 | I7: 10500 | J7: 105000 | L7: -105000 | N7: 100
A8: 46044 | B8: 003 | C8: {=IF(B8="", "", XLOOKUP(B8, Inventory!D:D,Inventory!E:E,"No Name Found"))} -> JC Global | D8: Credit | E8: Transfer | F8: Chocolate Biscuits | G8: =IF(F8="", "", VLOOKUP(F8, Inventory!A:BZ, 3, FALSE) - SUMIF($F$1:$F7, F8, $H$1:$H7)) -> 128 | H8: 40 | I8: 11950 | J8: 478000 | K8: 478000 | L8: 0 | N8: 88
A9: 46046 | B9: 001 | C9: {=IF(B9="", "", XLOOKUP(B9, Inventory!D:D,Inventory!E:E,"No Name Found"))} -> Mama Ada | D9: Credit | E9: Transfer | F9: Nice_Biscuits | G9: =IF(F9="", "", VLOOKUP(F9, Inventory!A:BZ, 3, FALSE) - SUMIF($F$1:$F8, F9, $H$1:$H8)) -> 117 | H9: 32 | I9: 8200 | J9: 262400 | K9: 300000 | L9: 37600 | N9: 85
A10: 46047 | B10: 18 | C10: {=IF(B10="", "", XLOOKUP(B10, Inventory!D:D,Inventory!E:E,"No Name Found"))} -> Moses Hiltop | D10: Debit | F10: Rich Tea Biscuit: | G10: =IF(F10="", "", VLOOKUP(F10, Inventory!A:BZ, 3, FALSE) - SUMIF($F$1:$F9, F10, $H$1:$H9)) -> 96 | H10: 12 | I10: 6200 | J10: 74400 | L10: -74400 | N10: 84
A11: 46048 | B11: 11 | C11: {=IF(B11="", "", XLOOKUP(B11, Inventory!D:D,Inventory!E:E,"No Name Found"))} -> Mama Emma | D11: Credit | E11: Cash | F11: Cabin Biscuit | G11: =IF(F11="", "", VLOOKUP(F11, Inventory!A:BZ, 3, FALSE) - SUMIF($F$1:$F10, F11, $H$1:$H10)) -> 70 | H11: 5 | I11: 4200 | J11: 21000 | K11: 21000 | L11: 0 | N11: 65
A12: 46049 | B12: 11 | C12: {=IF(B12="", "", XLOOKUP(B12, Inventory!D:D,Inventory!E:E,"No Name Found"))} -> Mama Emma | D12: Credit | E12: Transfer | F12: Digestives | G12: =IF(F12="", "", VLOOKUP(F12, Inventory!A:BZ, 3, FALSE) - SUMIF($F$1:$F11, F12, $H$1:$H11)) -> 214 | H12: 12 | I12: 6800 | J12: 81600 | K12: 81600 | L12: 0 | N12: 202
C13: {=IF(B13="", "", XLOOKUP(B13, Inventory!D:D,Inventory!E:E,"No Name Found"))} | G13: =IF(F13="", "", VLOOKUP(F13, Inventory!A:BZ, 3, FALSE) - SUMIF($F$1:$F12, F13, $H$1:$H12))
C14: {=IF(B14="", "", XLOOKUP(B14, Inventory!D:D,Inventory!E:E,"No Name Found"))} | G14: =IF(F14="", "", VLOOKUP(F14, Inventory!A:BZ, 3, FALSE) - SUMIF($F$1:$F13, F14, $H$1:$H13))
C15: {=IF(B15="", "", XLOOKUP(B15, Inventory!D:D,Inventory!E:E,"No Name Found"))} | G15: =IF(F15="", "", VLOOKUP(F15, Inventory!A:BZ, 3, FALSE) - SUMIF($F$1:$F14, F15, $H$1:$H14))
C16: {=IF(B16="", "", XLOOKUP(B16, Inventory!D:D,Inventory!E:E,"No Name Found"))} | G16: =IF(F16="", "", VLOOKUP(F16, Inventory!A:BZ, 3, FALSE) - SUMIF($F$1:$F15, F16, $H$1:$H15))
C17: {=IF(B17="", "", XLOOKUP(B17, Inventory!D:D,Inventory!E:E,"No Name Found"))} | G17: =IF(F17="", "", VLOOKUP(F17, Inventory!A:BZ, 3, FALSE) - SUMIF($F$1:$F16, F17, $H$1:$H16))
C18: {=IF(B18="", "", XLOOKUP(B18, Inventory!D:D,Inventory!E:E,"No Name Found"))} | G18: =IF(F18="", "", VLOOKUP(F18, Inventory!A:BZ, 3, FALSE) - SUMIF($F$1:$F17, F18, $H$1:$H17))
C19: {=IF(B19="", "", XLOOKUP(B19, Inventory!D:D,Inventory!E:E,"No Name Found"))} | G19: =IF(F19="", "", VLOOKUP(F19, Inventory!A:BZ, 3, FALSE) - SUMIF($F$1:$F18, F19, $H$1:$H18))
C20: {=IF(B20="", "", XLOOKUP(B20, Inventory!D:D,Inventory!E:E,"No Name Found"))} | G20: =IF(F20="", "", VLOOKUP(F20, Inventory!A:BZ, 3, FALSE) - SUMIF($F$1:$F19, F20, $H$1:$H19))
C21: {=IF(B21="", "", XLOOKUP(B21, Inventory!D:D,Inventory!E:E,"No Name Found"))} | G21: =IF(F21="", "", VLOOKUP(F21, Inventory!A:BZ, 3, FALSE) - SUMIF($F$1:$F20, F21, $H$1:$H20))
C22: {=IF(B22="", "", XLOOKUP(B22, Inventory!D:D,Inventory!E:E,"No Name Found"))} | G22: =IF(F22="", "", VLOOKUP(F22, Inventory!A:BZ, 3, FALSE) - SUMIF($F$1:$F21, F22, $H$1:$H21))
C23: {=IF(B23="", "", XLOOKUP(B23, Inventory!D:D,Inventory!E:E,"No Name Found"))} | G23: =IF(F23="", "", VLOOKUP(F23, Inventory!A:BZ, 3, FALSE) - SUMIF($F$1:$F22, F23, $H$1:$H22))
C24: {=IF(B24="", "", XLOOKUP(B24, Inventory!D:D,Inventory!E:E,"No Name Found"))} | G24: =IF(F24="", "", VLOOKUP(F24, Inventory!A:BZ, 3, FALSE) - SUMIF($F$1:$F23, F24, $H$1:$H23))
... C5998: {=IF(B5998="", "", XLOOKUP(B5998, Inventory!D:D,Inventory!E:E,"No Name Found"))} | G5998: =IF(F5998="", "", VLOOKUP(F5998, Inventory!A:BZ, 3, FALSE) - SUMIF($F$1:$F5997, F5998, $H$1:$H5997))
I5999: =SUM(I2:I5998) -> 121860 | J5999: =SUM(J2:J5998) -> 3519550 | K5999: =SUM(K2:K5998) -> 3330600 | L5999: =SUM(L2:L5998) -> -188950

Sheet Admin
A1: Posting Date | B1: Customer Code | C1: Customer Name | D1: Particulars | E1: Reference | F1: Products | G1: Quantity | H1: Qty Purchase | I1: Price/Qty | J1: Total Price | K1: Payment Received | L1: Debit | M1: Remark/Teller Date/Number | N1: Stock Balance | O1: Balance Stock Value | R1: Customer Details | S1: Total Amount | T1: Paid | U1: Balance
A2: {=IF(Sales_Person!A2:A5998="", "", Sales_Person!A2:A5998)} -> 46032 | B2: {=IF(Sales_Person!B2:B5998="", "", Sales_Person!B2:B5998)} -> 001 | C2: {=IF(Sales_Person!C2:C5998="", "", Sales_Person!C2:C5998)} -> Mama Ada | D2: {=IF(Sales_Person!D2:D5998="", "", Sales_Person!D2:D5998)} -> Credit | E2: {=IF(Sales_Person!E2:E5998="", "", Sales_Person!E2:E5998)} -> Transfer | F2: {=IF(Sales_Person!F2:F5998="", "", Sales_Person!F2:F5998)} -> Gala | G2: {=IF(Sales_Person!G2:G5998="", "", Sales_Person!G2:G5998)} -> 130 | H2: 20 | I2: {=IF(Sales_Person!I2:I5998="", "", Sales_Person!I2:I5998)} -> 10500 | J2: {=IF(Sales_Person!J2:J5998="", "", Sales_Person!J2:J5998)} -> 210000 | K2: 150000 | L2: {=IF(Sales_Person!L2:L5998="", "", Sales_Person!L2:L5998)} -> -60000 | M2: {=IF(Sales_Person!M2:M5998="", "", Sales_Person!M2:M5998)} | N2: {=IF(Sales_Person!N2:N5998="", "", Sales_Person!N2:N5998)} -> 110 | O2: {=IF(N2:N5998="","",I2:I5998*N2:N5998)} -> 1155000 | Q2: Customer Name | R2: Mama Emma | S2: =SUMIF(C2:C5998,R2,J2:J5998) -> 102600 | T2: =SUMIF(C2:C5998,R2,K2:K5998) -> 102600 | U2: =SUMIF(C2:C5998,R2,L2:L5998) -> 0
A3: 46034 | B3: 002 | C3: Funmi Airport | D3: Credit | E3: Transfer | F3: Mini Chin Chin Packs | G3: 78 | H3: 40 | I3: 20000 | J3: 800000 | K3: 800000 | L3: 0 | N3: 38 | O3: 760000
A4: 46037 | B4: 001 | C4: Mama Ada | D4: Credit | E4: Transfer | F4: Peanut Snacks | G4: 114 | H4: 50 | I4: 12300 | J4: 615000 | K4: 1000000 | L4: 385000 | N4: 64 | O4: 787200
A5: 46042 | B5: 004 | C5: KC | D5: Debit | F5: Cheese Balls | G5: 160 | H5: 20 | I5: 14680 | J5: 293600 | L5: -293600 | N5: 140 | O5: 2055200
A6: 46044 | B6: 005 | C6: Chidi Market | D6: Credit | E6: Cash | F6: Short_Bread | G6: 95 | H6: 35 | I6: 16530 | J6: 578550 | K6: 500000 | L6: -78550 | N6: 60 | O6: 991800
A7: 46044 | B7: 006 | C7: Angela N | D7: Debit | F7: Gala | G7: 110 | H7: 10 | I7: 10500 | J7: 105000 | L7: -105000 | N7: 100 | O7: 1050000
A8: 46044 | B8: 003 | C8: JC Global | D8: Credit | E8: Transfer | F8: Chocolate Biscuits | G8: 128 | H8: 40 | I8: 11950 | J8: 478000 | K8: 478000 | L8: 0 | N8: 88 | O8: 1051600 | Q8: Product Name | R8: Details | S8: Total Stock | T8: Stock Sold | U8: Balance Stock
A9: 46046 | B9: 001 | C9: Mama Ada | D9: Credit | E9: Transfer | F9: Nice_Biscuits | G9: 117 | H9: 32 | I9: 8200 | J9: 262400 | K9: 300000 | L9: 37600 | N9: 85 | O9: 697000 | R9: Ginger_Biscuits | S9: =SUMIF(Inventory!A2:A100,Admin!R9,Inventory!C2:C100) -> 25 | T9: =SUMIF(F2:F100,R9,H2:H100) -> 0 | U9: =S9-T9 -> 25
A10: 46047 | B10: 18 | C10: Moses Hiltop | D10: Debit | F10: Rich Tea Biscuit: | G10: 96 | H10: 12 | I10: 6200 | J10: 74400 | L10: -74400 | N10: 84 | O10: 520800
A11: 46048 | B11: 11 | C11: Mama Emma | D11: Credit | E11: Cash | F11: Cabin Biscuit | G11: 70 | H11: 5 | I11: 4200 | J11: 21000 | K11: 21000 | L11: 0 | N11: 65 | O11: 273000
A12: 46049 | B12: 11 | C12: Mama Emma | D12: Credit | E12: Transfer | F12: Digestives | G12: 214 | H12: 12 | I12: 6800 | J12: 81600 | K12: 81600 | L12: 0 | N12: 202 | O12: 1373600

Sheet Summary
